{
  "project_info": {
    "project_number": "729813118801",
    "project_id": "kasper-tech-task",
    "storage_bucket": "kasper-tech-task.appspot.com"
  },
  "client": [
    {
      "client_info": {
        "mobilesdk_app_id": "1:729813118801:android:9dc0b521455c0d7428ed70",
        "android_client_info": {
          "package_name": "com.example.kasper_tech_task"
        }
      },
      "oauth_client": [
        {
          "client_id": "729813118801-p8nttncp6oivked7f68kr5djhmrg6gen.apps.googleusercontent.com",
          "client_type": 3
        }
      ],
      "api_key": [
        {
          "current_key": "AIzaSyBVqMNeHRt-u0tlmUNSg7ZMVgVln52rQbM"
        }
      ],
      "services": {
        "appinvite_service": {
          "other_platform_oauth_client": [
            {
              "client_id": "729813118801-p8nttncp6oivked7f68kr5djhmrg6gen.apps.googleusercontent.com",
              "client_type": 3
            }
          ]
        }
      }
    }
  ],
  "configuration_version": "1"
}